lm_datasets/__init__.py
lm_datasets/chunkify_datasets.py
lm_datasets/collect_metrics.py
lm_datasets/compose_dataset.py
lm_datasets/convert_parquet_to_jsonl.py
lm_datasets/extract_text.py
lm_datasets/hf_tokenize_parquet_dataset.py
lm_datasets/print_stats.py
lm_datasets/shuffle_datasets.py
lm_datasets/train_sp_tokenizer.py
lm_datasets/commands/__init__.py
lm_datasets/commands/chunkify_command.py
lm_datasets/commands/collect_metrics_command.py
lm_datasets/commands/compose_command.py
lm_datasets/commands/convert_parquet_to_jsonl_command.py
lm_datasets/commands/extract_text_command.py
lm_datasets/commands/hf_upload_command.py
lm_datasets/commands/lm_datasets_cli.py
lm_datasets/commands/print_stats_command.py
lm_datasets/commands/shuffle_command.py
lm_datasets/commands/train_tokenizer_command.py
lm_datasets/datasets/__init__.py
lm_datasets/datasets/base.py
lm_datasets/datasets/dataset_registry.py
lm_datasets/datasets/hf_dataset.py
lm_datasets/datasets/jsonl_dataset.py
lm_datasets/datasets/parquet_dataset.py
lm_datasets/datasets/bg/__init__.py
lm_datasets/datasets/bg/bgnc_admin_eur.py
lm_datasets/datasets/bg/bgnc_news_corpus.py
lm_datasets/datasets/bg/bulgarian_news.py
lm_datasets/datasets/bg/bulnc.py
lm_datasets/datasets/code/__init__.py
lm_datasets/datasets/code/starcoder.py
lm_datasets/datasets/cs/__init__.py
lm_datasets/datasets/cs/cs_en_parallel.py
lm_datasets/datasets/cs/syn_v9.py
lm_datasets/datasets/da/__init__.py
lm_datasets/datasets/da/danewsroom.py
lm_datasets/datasets/da/danish_gigaword.py
lm_datasets/datasets/da/danish_parliament_corpus.py
lm_datasets/datasets/da/dk_clarin.py
lm_datasets/datasets/de/__init__.py
lm_datasets/datasets/de/dewac.py
lm_datasets/datasets/de/openlegaldata.py
lm_datasets/datasets/el/__init__.py
lm_datasets/datasets/el/greek_legal_code.py
lm_datasets/datasets/el/greek_web_corpus.py
lm_datasets/datasets/en/__init__.py
lm_datasets/datasets/en/dialogstudio.py
lm_datasets/datasets/en/math_amps.py
lm_datasets/datasets/en/pes2o.py
lm_datasets-0.0.2.dist-info/LICENSE
lm_datasets-0.0.2.dist-info/METADATA
lm_datasets-0.0.2.dist-info/WHEEL
lm_datasets-0.0.2.dist-info/entry_points.txt
lm_datasets-0.0.2.dist-info/top_level.txt
lm_datasets-0.0.2.dist-info/RECORD
